<annotation>
	<folder>pelicam-training</folder>
	<filename>images (59).jpeg</filename>
	<path>/Users/Calvin/Downloads/pelicam-training/images (59).jpeg</path>
	<source>
		<database>Unknown</database>
	</source>
	<size>
		<width>199</width>
		<height>254</height>
		<depth>3</depth>
	</size>
	<segmented>0</segmented>
	<object>
		<name>pelican</name>
		<pose>Unspecified</pose>
		<truncated>0</truncated>
		<difficult>0</difficult>
		<bndbox>
			<xmin>57</xmin>
			<ymin>24</ymin>
			<xmax>138</xmax>
			<ymax>224</ymax>
		</bndbox>
	</object>
</annotation>
